geoveil_cn0/__init__.py
geoveil_cn0/geoveil_cn0.cpython-312-x86_64-linux-gnu.so
geoveil_cn0-0.3.6.dist-info/METADATA
geoveil_cn0-0.3.6.dist-info/WHEEL
geoveil_cn0-0.3.6.dist-info/licenses/LICENSE
geoveil_cn0-0.3.6.dist-info/RECORD
