Metadata-Version: 2.4
Name: geoveil-cn0
Version: 0.3.6
Classifier: Development Status :: 4 - Beta
Classifier: Intended Audience :: Science/Research
Classifier: Intended Audience :: Developers
Classifier: License :: OSI Approved :: MIT License
Classifier: Operating System :: OS Independent
Classifier: Programming Language :: Python :: 3
Classifier: Programming Language :: Python :: 3.8
Classifier: Programming Language :: Python :: 3.9
Classifier: Programming Language :: Python :: 3.10
Classifier: Programming Language :: Python :: 3.11
Classifier: Programming Language :: Python :: 3.12
Classifier: Programming Language :: Rust
Classifier: Topic :: Scientific/Engineering
Classifier: Topic :: Scientific/Engineering :: GIS
Classifier: Topic :: Scientific/Engineering :: Physics
Requires-Dist: pytest ; extra == 'dev'
Requires-Dist: numpy ; extra == 'dev'
Requires-Dist: pandas ; extra == 'dev'
Requires-Dist: plotly ; extra == 'dev'
Requires-Dist: ipywidgets ; extra == 'notebook'
Requires-Dist: jupyter ; extra == 'notebook'
Requires-Dist: plotly ; extra == 'notebook'
Requires-Dist: pandas ; extra == 'notebook'
Requires-Dist: numpy ; extra == 'notebook'
Provides-Extra: dev
Provides-Extra: notebook
License-File: LICENSE
Summary: GNSS CN0 Analysis Library - Interference, Jamming & Spoofing Detection
Keywords: gnss,gps,glonass,galileo,beidou,cn0,snr,signal-quality,rinex,navigation,ephemeris,interference,jamming,spoofing,multipath,anomaly-detection
Author-email: Miluta Dulea-Flueras <miluta.flueras@cartografie.ro>
Requires-Python: >=3.8
Project-URL: Changelog, https://github.com/miluta7/geoveil-cn0/releases
Project-URL: Documentation, https://github.com/miluta7/geoveil-cn0#readme
Project-URL: Homepage, https://github.com/miluta7/geoveil-cn0
Project-URL: Issues, https://github.com/miluta7/geoveil-cn0/issues
Project-URL: Repository, https://github.com/miluta7/geoveil-cn0
